autonet_cumulus/__init__.py
autonet_cumulus/__version__.py
autonet_cumulus/commands.py
autonet_cumulus/driver.py
autonet_cumulus/tasks/__init__.py
autonet_cumulus/tasks/interface.py
autonet_cumulus/tasks/lag.py
autonet_cumulus/tasks/vlan.py
autonet_cumulus/tasks/vrf.py
autonet_cumulus/tasks/vxlan.py
autonet_cumulus-0.2.1.dist-info/LICENSE.txt
autonet_cumulus-0.2.1.dist-info/METADATA
autonet_cumulus-0.2.1.dist-info/WHEEL
autonet_cumulus-0.2.1.dist-info/entry_points.txt
autonet_cumulus-0.2.1.dist-info/top_level.txt
autonet_cumulus-0.2.1.dist-info/RECORD
