Metadata-Version: 2.1
Name: autonet-cumulus
Version: 0.2.1
Summary: Network device configuration abstraction API
Home-page: https://github.com/Connectria/autonet-cumulus
Author: Ken Vondersaar
Author-email: kvondersaar@connectria.com
License: UNKNOWN
Project-URL: Bug Tracker, https://github.com/Connectria/autonet-cumulus
Project-URL: Documentation, https://connectria.github.io/autone-cumulus
Platform: UNKNOWN
Classifier: Programming Language :: Python :: 3.9
Classifier: Programming Language :: Python :: 3.10
Classifier: Development Status :: 4 - Beta
Classifier: License :: OSI Approved :: MIT License
Classifier: Operating System :: OS Independent
Requires-Python: >=3.9
License-File: LICENSE.txt
Requires-Dist: autonet-api
Requires-Dist: parallel-ssh
